{
    "items": {
        "AJ": {
            "embedded": [
                2220,
                7476,
                87
            ],
            "frame": [
                187,
                9509,
                87
            ]
        },
        "MS": {
            "interruptive": [
                2220,
                7476,
                87
            ],
            "original": [
                187,
                2030,
                7566
            ]
        }
    },
    "segmentation_type": "linear"
}