{
    "items": {
        "AJ": {
            "embedded": [
                665,
                21902,
                2221
            ],
            "original": [
                76,
                24418,
                294
            ]
        },
        "MS": {
            "embedded": [
                665,
                21902,
                2221
            ],
            "original": [
                76,
                24418,
                294
            ]
        }
    },
    "segmentation_type": "linear"
}